README.md
setup.py
sekg/__init__.py
sekg/meta.py
sekg.egg-info/PKG-INFO
sekg.egg-info/SOURCES.txt
sekg.egg-info/dependency_links.txt
sekg.egg-info/requires.txt
sekg.egg-info/top_level.txt
sekg/constant/__init__.py
sekg/constant/code.py
sekg/constant/constant.py
sekg/constant/directive.py
sekg/download_tool/__init__.py
sekg/download_tool/download_manager.py
sekg/graph/__init__.py
sekg/graph/accessor.py
sekg/graph/creator.py
sekg/graph/factory.py
sekg/graph/index_accessor.py
sekg/graph/label_accessor.py
sekg/graph/metadata_accessor.py
sekg/graph/builder/__init__.py
sekg/graph/builder/code_kg_builder.py
sekg/graph/el/__init__.py
sekg/graph/el/base.py
sekg/graph/el/ngram_anchor_link.py
sekg/graph/exporter/__init__.py
sekg/graph/exporter/graph_data.py
sekg/graph/exporter/scheme_graph_data.py
sekg/graph/exporter/scheme_graph_util.py
sekg/graph/exporter/weight_graph_data.py
sekg/graph/util/__init__.py
sekg/graph/util/name_searcher.py
sekg/graph/util/property_searcher.py
sekg/ir/__init__.py
sekg/ir/doc/__init__.py
sekg/ir/doc/wrapper.py
sekg/ir/models/__init__.py
sekg/ir/models/avg_bert.py
sekg/ir/models/avg_w2v.py
sekg/ir/models/base.py
sekg/ir/models/bm25.py
sekg/ir/models/compound.py
sekg/ir/models/lda.py
sekg/ir/models/tf_idf.py
sekg/ir/models/tfidf_w2v.py
sekg/ir/models/n2v/__init__.py
sekg/ir/models/n2v/el/__init__.py
sekg/ir/models/n2v/el/el_tfidf_n2v.py
sekg/ir/models/n2v/el/el_tfidf_n2v_max.py
sekg/ir/models/n2v/el/el_tfidf_n2v_ws.py
sekg/ir/models/n2v/svm/__init__.py
sekg/ir/models/n2v/svm/avg_n2v.py
sekg/ir/models/n2v/svm/filter_semantic_tfidf_n2v.py
sekg/ir/models/n2v/svm/filter_tfidf_n2v.py
sekg/ir/models/n2v/svm/tfidf_n2v.py
sekg/ir/models/util/__init__.py
sekg/ir/models/util/load.py
sekg/ir/preprocessor/__init__.py
sekg/ir/preprocessor/base.py
sekg/ir/preprocessor/code_text.py
sekg/ir/preprocessor/ngram.py
sekg/ir/preprocessor/spacy.py
sekg/metric/__init__.py
sekg/metric/ir.py
sekg/model/__init__.py
sekg/model/node2vec/__init__.py
sekg/model/node2vec/main.py
sekg/model/node2vec/node2vec.py
sekg/model/node2vec/train.py
sekg/model/word2vec/__init__.py
sekg/model/word2vec/tune_word2vec.py
