Metadata-Version: 1.0
Name: sekg
Version: 0.10.3.19
Summary: knowledge graph util for software engineering
Home-page: https://github.com/FudanSELab/sekg
Author: FDSEKG
Author-email: lmwtclmwtc@outlook.com
License: Apache License, Version 2.0
Keywords: pip,kg,se
Platform: any
